rainbow_print/__init__.py
rainbow_print/rainbow.py
rainbow_print/singleton.py
rainbow_print-1.0.5.dist-info/LICENSE.txt
rainbow_print-1.0.5.dist-info/METADATA
rainbow_print-1.0.5.dist-info/WHEEL
rainbow_print-1.0.5.dist-info/top_level.txt
rainbow_print-1.0.5.dist-info/RECORD
