Metadata-Version: 2.1
Name: rainbow-print
Version: 1.0.5
Summary: Rainbow Print adds colors to the standard outputs to ease the process of monitoring respective data / metrics
Home-page: https://github.com/kingspp/rainbow-print
Author: Prathyush SP
Author-email: kingspprathyush@gmail.com
License: UNKNOWN
Project-URL: Bug Reports, https://github.com/kingspp/rainbow-print/issues
Project-URL: Funding, https://donate.pypi.org
Project-URL: Say Thanks!, https://saythanks.io/to/kingspprathyush@gmail.com
Project-URL: Source, https://github.com/kingspp/rainbow-print
Keywords: rainbow_print,print,logging,colors
Platform: UNKNOWN
Classifier: Development Status :: 4 - Beta
Classifier: Intended Audience :: Developers
Classifier: Topic :: Software Development :: Build Tools
Classifier: License :: OSI Approved :: MIT License
Classifier: Programming Language :: Python :: 3.5
Classifier: Programming Language :: Python :: 3.6
Classifier: Programming Language :: Python :: 3 :: Only
Requires-Python: >=3.5, <4
Requires-Dist: sty
Provides-Extra: dev
Requires-Dist: check-manifest ; extra == 'dev'
Provides-Extra: test
Requires-Dist: coverage ; extra == 'test'
